LICENSE
MANIFEST.in
README.rst
setup.py
tabgeo/__init__.py
tabgeo/core.py
tabgeo.egg-info/PKG-INFO
tabgeo.egg-info/SOURCES.txt
tabgeo.egg-info/dependency_links.txt
tabgeo.egg-info/not-zip-safe
tabgeo.egg-info/top_level.txt
tabgeo/data/tabgeo_country_v4.dat