Metadata-Version: 1.1
Name: tabgeo
Version: 0.2
Summary: Geolocation database to determine country code (ISO 3166-1 alpha-2) by IP
Home-page: UNKNOWN
Author: Alex Klimenka
Author-email: nimda7@gmail.com
License: GNU Affero General Public License v3
Keywords: geo,geoip,geolocation,ISO 3166-1
Platform: any
Classifier: Development Status :: 4 - Beta
Classifier: Environment :: Web Environment
Classifier: Intended Audience :: Developers
Classifier: Programming Language :: Python :: 2.7
